subtitle_translator/__init__.py
subtitle_translator/cli.py
subtitle_translator/config.py
subtitle_translator/logger.py
subtitle_translator/openai_client.py
subtitle_translator/srt_translator.py
subtitle_translator/location_utils/__init__.py
subtitle_translator/location_utils/config.py
subtitle_translator/location_utils/location.py
subtransai-1.0.4.dist-info/AUTHORS.rst
subtransai-1.0.4.dist-info/LICENSE
subtransai-1.0.4.dist-info/METADATA
subtransai-1.0.4.dist-info/WHEEL
subtransai-1.0.4.dist-info/entry_points.txt
subtransai-1.0.4.dist-info/top_level.txt
subtransai-1.0.4.dist-info/RECORD
