Metadata-Version: 2.2
Name: subtransAI
Version: 1.0.4
Summary: Python project using AI for subtitle translation.
Author-email: Tyrion <maple_leaf_7@msn.com>
Maintainer-email: Tyrion <maple_leaf_7@msn.com>
License: MIT license
Project-URL: bugs, https://github.com/tyrion-wang/subtitle_translator/issues
Project-URL: changelog, https://github.com/tyrion-wang/subtitle_translator/blob/master/changelog.md
Project-URL: homepage, https://github.com/tyrion-wang/subtitle_translator
License-File: LICENSE
License-File: AUTHORS.rst
Requires-Dist: typer~=0.13.1
Requires-Dist: openai~=1.55.0
Requires-Dist: srt~=3.5.3
Requires-Dist: rich~=13.9.4
Provides-Extra: dev
Requires-Dist: coverage; extra == "dev"
Requires-Dist: mypy; extra == "dev"
Requires-Dist: pytest; extra == "dev"
Requires-Dist: ruff; extra == "dev"
